tray_manager/__init__.py
tray_manager/tray_manager.py
tray_manager-1.0.5.dist-info/licenses/COPYING
tray_manager-1.0.5.dist-info/licenses/COPYING.LGPL
tray_manager-1.0.5.dist-info/METADATA
tray_manager-1.0.5.dist-info/WHEEL
tray_manager-1.0.5.dist-info/top_level.txt
tray_manager-1.0.5.dist-info/RECORD
