Metadata-Version: 2.4
Name: tray_manager
Version: 1.0.5
Summary: An "easier" version to use of the pystray library (https://github.com/moses-palmer/pystray by Moses Palmér)
Home-page: https://github.com/Adastram1/tray_manager
Author: Adastram
Author-email: 
License: GNU Lesser General Public License v3 (LGPLv3)
Keywords: python,manager,system tray,pystray
Classifier: Development Status :: 4 - Beta
Classifier: Intended Audience :: End Users/Desktop
Classifier: Intended Audience :: Developers
Classifier: License :: OSI Approved :: GNU Lesser General Public License v3 (LGPLv3)
Classifier: Operating System :: Microsoft :: Windows
Classifier: Operating System :: MacOS :: MacOS X
Classifier: Operating System :: POSIX :: Linux
Classifier: Topic :: Desktop Environment
Classifier: Programming Language :: Python
Classifier: Programming Language :: Python :: 3
License-File: COPYING
License-File: COPYING.LGPL
Requires-Dist: pystray
Requires-Dist: pillow
Dynamic: author
Dynamic: classifier
Dynamic: description
Dynamic: description-content-type
Dynamic: home-page
Dynamic: keywords
Dynamic: license
Dynamic: license-file
Dynamic: requires-dist
Dynamic: summary
